{
	"partitions" : [
		{
			"name" : "Top",
			"pins" : [
				{
					"name" : "timeRemaining[0]",
					"strict" : false
				},
				{
					"name" : "timeRemaining[1]",
					"strict" : false
				},
				{
					"name" : "timeRemaining[2]",
					"strict" : false
				},
				{
					"name" : "timeRemaining[3]",
					"strict" : false
				},
				{
					"name" : "timeRemaining[4]",
					"strict" : false
				},
				{
					"name" : "timeRemaining[5]",
					"strict" : false
				},
				{
					"name" : "timeRemaining[6]",
					"strict" : false
				},
				{
					"name" : "Principal_Road[0]",
					"strict" : false
				},
				{
					"name" : "Principal_Road[1]",
					"strict" : false
				},
				{
					"name" : "Principal_Road[2]",
					"strict" : false
				},
				{
					"name" : "Secondary_Road[0]",
					"strict" : false
				},
				{
					"name" : "Secondary_Road[1]",
					"strict" : false
				},
				{
					"name" : "Secondary_Road[2]",
					"strict" : false
				},
				{
					"name" : "Principal_Pedestrian[0]",
					"strict" : false
				},
				{
					"name" : "Principal_Pedestrian[1]",
					"strict" : false
				},
				{
					"name" : "Secondary_Pedestrian[0]",
					"strict" : false
				},
				{
					"name" : "Secondary_Pedestrian[1]",
					"strict" : false
				},
				{
					"name" : "StateFlag[0]",
					"strict" : false
				},
				{
					"name" : "StateFlag[1]",
					"strict" : false
				},
				{
					"name" : "clock1Hz",
					"strict" : false
				},
				{
					"name" : "reset",
					"strict" : false
				}
			]
		}
	]
}